kinematics5/OneD.py
kinematics5/__init__.py
kinematics5-0.0.5.dist-info/LICENSE
kinematics5-0.0.5.dist-info/METADATA
kinematics5-0.0.5.dist-info/WHEEL
kinematics5-0.0.5.dist-info/top_level.txt
kinematics5-0.0.5.dist-info/RECORD
