Metadata-Version: 2.1
Name: kinematics5
Version: 0.0.5
Summary: A package for solving 1D kinematics problems.
Home-page: https://github.com/MED-1996/kinematics5
Author: Mitchell_Daddario
Author-email: mitchelldaddario@gmail.com
License: UNKNOWN
Platform: UNKNOWN
Classifier: Programming Language :: Python :: 3
Classifier: License :: OSI Approved :: MIT License
Classifier: Operating System :: OS Independent
Requires-Python: >=3.6
License-File: LICENSE
